{
  "title": "Tutorial:Production line",
  "pageid": 3196,
  "categories": [
    "Tutorials"
  ],
  "sections": [
    "Reading building interfaces",
    "Miner",
    "Smelter",
    "Constructor",
    "Per-cycle and per-minute rates",
    "Conveyor Belt",
    "Storage Container",
    "Overclocking",
    "Splitting and merging",
    "Miner",
    "Smelter",
    "Constructor (Wire)",
    "Constructor (Cable)",
    "Conveyor Belt",
    "Storage Container",
    "Overclocking and Flow Rate",
    "Miner",
    "Smelter",
    "Conveyor Belt",
    "Manifold",
    "Fractions and decimals",
    "Build more machines",
    "Overclocking and Underclocking",
    "Overclock the Miner",
    "Overclock the Constructor",
    "Underclock the last machine",
    "Underclock all machines",
    "Complex production line",
    "Miner",
    "Smelter",
    "Dividing Resources",
    "Reinforced Iron Plate",
    "Iron Plate",
    "Screw",
    "Iron Rod",
    "Math it out",
    "Constructor (Iron Plate)",
    "Constructor (Iron Rod)",
    "Constructor (Screw)",
    "Assembler (Reinforced Iron Plate)",
    "Conveyor Belt",
    "Online tools"
  ],
  "url": "https://satisfactory.wiki.gg/wiki/Tutorial:Production_line"
}